{
  "name": "cries/poliwhirl-latest.mp3",
  "bucket": "guessthecry.firebasestorage.app",
  "metageneration": 1,
  "generation": 1765525684454,
  "contentType": "audio/mpeg",
  "storageClass": "STANDARD",
  "contentDisposition": "inline",
  "downloadTokens": [
    "4108fd69-fc53-4f91-86c5-88ce523e793b"
  ],
  "etag": "gsNZIuee2CQekmxysBezaa/bbo8",
  "customMetadata": {},
  "timeCreated": "2025-12-12T07:48:04.454Z",
  "updated": "2025-12-12T07:48:04.454Z",
  "size": 3464,
  "md5Hash": "MXZeKsvNPEd8oWtEMnXhVQ==",
  "crc32c": "2812612884"
}