{
  "name": "cries/spoink-latest.mp3",
  "bucket": "guessthecry.firebasestorage.app",
  "metageneration": 1,
  "generation": 1765525684380,
  "contentType": "audio/mpeg",
  "storageClass": "STANDARD",
  "contentDisposition": "inline",
  "downloadTokens": [
    "f1f4aa75-c332-4559-b884-dbfe9def98b3"
  ],
  "etag": "oPvSCBUJ3rBuZTLJxJGXdeaqO4A",
  "customMetadata": {},
  "timeCreated": "2025-12-12T07:48:04.380Z",
  "updated": "2025-12-12T07:48:04.380Z",
  "size": 3248,
  "md5Hash": "KEKHpDozEubWiwI2V8uxaw==",
  "crc32c": "1972862055"
}