{
  "name": "cries/blaziken-legacy.mp3",
  "bucket": "guessthecry.firebasestorage.app",
  "metageneration": 1,
  "generation": 1765525685611,
  "contentType": "audio/mpeg",
  "storageClass": "STANDARD",
  "contentDisposition": "inline",
  "downloadTokens": [
    "34f90cd0-3431-47d2-9f5a-8962ba3b7156"
  ],
  "etag": "QjX6BXPfOS1y1l6IQRfDYJ/Nwfg",
  "customMetadata": {},
  "timeCreated": "2025-12-12T07:48:05.611Z",
  "updated": "2025-12-12T07:48:05.611Z",
  "size": 3491,
  "md5Hash": "0Iu0NjWciC4l5wlZQlGJHw==",
  "crc32c": "4053834222"
}