{
  "name": "cries/slaking-latest.mp3",
  "bucket": "guessthecry.firebasestorage.app",
  "metageneration": 1,
  "generation": 1765525684074,
  "contentType": "audio/mpeg",
  "storageClass": "STANDARD",
  "contentDisposition": "inline",
  "downloadTokens": [
    "0ccc15e5-97cd-4a7a-8074-51a1dae852b5"
  ],
  "etag": "pwsYKALRQIflr0DA7Q+NnRHzHoo",
  "customMetadata": {},
  "timeCreated": "2025-12-12T07:48:04.074Z",
  "updated": "2025-12-12T07:48:04.074Z",
  "size": 4328,
  "md5Hash": "w2vCNWJYP7KeBdMRXmqbig==",
  "crc32c": "2943199763"
}