{
  "name": "cries/archen-legacy.mp3",
  "bucket": "guessthecry.firebasestorage.app",
  "metageneration": 1,
  "generation": 1765525686159,
  "contentType": "audio/mpeg",
  "storageClass": "STANDARD",
  "contentDisposition": "inline",
  "downloadTokens": [
    "77c44745-5b99-4e4d-9814-dab627f83304"
  ],
  "etag": "s8OM0zetgCfJhJBe69TuxxLnq7I",
  "customMetadata": {},
  "timeCreated": "2025-12-12T07:48:06.159Z",
  "updated": "2025-12-12T07:48:06.159Z",
  "size": 4760,
  "md5Hash": "khbPpZ41JtsG3L3gcnaleA==",
  "crc32c": "1864985498"
}