{
  "name": "cries/baxcalibur-latest.mp3",
  "bucket": "guessthecry.firebasestorage.app",
  "metageneration": 1,
  "generation": 1765525683556,
  "contentType": "audio/mpeg",
  "storageClass": "STANDARD",
  "contentDisposition": "inline",
  "downloadTokens": [
    "f46bb7af-d496-4451-a2a7-5df1003b7b3a"
  ],
  "etag": "hlWMnltES8aEqgQyKCtywYbu9Z4",
  "customMetadata": {},
  "timeCreated": "2025-12-12T07:48:03.556Z",
  "updated": "2025-12-12T07:48:03.556Z",
  "size": 20780,
  "md5Hash": "x1LrD4WX67UMtMJyo09COA==",
  "crc32c": "3000208108"
}