{
  "name": "cries/combusken-latest.mp3",
  "bucket": "guessthecry.firebasestorage.app",
  "metageneration": 1,
  "generation": 1765525684365,
  "contentType": "audio/mpeg",
  "storageClass": "STANDARD",
  "contentDisposition": "inline",
  "downloadTokens": [
    "4590c53c-fbe0-4f21-9815-f106d0d91825"
  ],
  "etag": "aQYuDqNoX8vLvVYfzLdRD0bH5cw",
  "customMetadata": {},
  "timeCreated": "2025-12-12T07:48:04.365Z",
  "updated": "2025-12-12T07:48:04.365Z",
  "size": 8432,
  "md5Hash": "R/u94q0n/zIxRTPamxANAg==",
  "crc32c": "2793967706"
}