{
  "name": "cries/kilowattrel-latest.mp3",
  "bucket": "guessthecry.firebasestorage.app",
  "metageneration": 1,
  "generation": 1765525683932,
  "contentType": "audio/mpeg",
  "storageClass": "STANDARD",
  "contentDisposition": "inline",
  "downloadTokens": [
    "216399c3-7afb-4bc2-8eba-ffe7c052ca80"
  ],
  "etag": "WWUqT/L+bKJwJBi2GaPWIdMemX0",
  "customMetadata": {},
  "timeCreated": "2025-12-12T07:48:03.932Z",
  "updated": "2025-12-12T07:48:03.932Z",
  "size": 12137,
  "md5Hash": "zxotqgEOdYTEO+7TSSTv/w==",
  "crc32c": "2875486891"
}