{
  "name": "cries/zygarde-latest.mp3",
  "bucket": "guessthecry.firebasestorage.app",
  "metageneration": 1,
  "generation": 1765525683926,
  "contentType": "audio/mpeg",
  "storageClass": "STANDARD",
  "contentDisposition": "inline",
  "downloadTokens": [
    "2769ca7a-913b-4999-90ef-e5c16cadfe05"
  ],
  "etag": "u6N1kmjerdNShQaPoXDVj3lLTWY",
  "customMetadata": {},
  "timeCreated": "2025-12-12T07:48:03.926Z",
  "updated": "2025-12-12T07:48:03.926Z",
  "size": 11456,
  "md5Hash": "C5APc0crnCTsiQRJSBHwcw==",
  "crc32c": "2920341773"
}