{
  "name": "cries/virizion-latest.mp3",
  "bucket": "guessthecry.firebasestorage.app",
  "metageneration": 1,
  "generation": 1765525684280,
  "contentType": "audio/mpeg",
  "storageClass": "STANDARD",
  "contentDisposition": "inline",
  "downloadTokens": [
    "fa9e1674-9376-4d1f-8203-3b96e230efe3"
  ],
  "etag": "Qq3yJuyzpLlqSQOim/NsPYsGc0s",
  "customMetadata": {},
  "timeCreated": "2025-12-12T07:48:04.280Z",
  "updated": "2025-12-12T07:48:04.280Z",
  "size": 7784,
  "md5Hash": "/N6DmPnJaBeNKsCy2hKZaA==",
  "crc32c": "936283864"
}