{
  "name": "cries/sylveon-latest.mp3",
  "bucket": "guessthecry.firebasestorage.app",
  "metageneration": 1,
  "generation": 1765525684403,
  "contentType": "audio/mpeg",
  "storageClass": "STANDARD",
  "contentDisposition": "inline",
  "downloadTokens": [
    "c7f66c64-8cb6-4843-9ad6-caca818f19cb"
  ],
  "etag": "BDu0nuEjWI1KGE8H7er9kAnOhEw",
  "customMetadata": {},
  "timeCreated": "2025-12-12T07:48:04.403Z",
  "updated": "2025-12-12T07:48:04.403Z",
  "size": 10160,
  "md5Hash": "bPOp9rxwfVVRvzz5cdEpFg==",
  "crc32c": "2596003242"
}