{
  "name": "cries/gliscor-latest.mp3",
  "bucket": "guessthecry.firebasestorage.app",
  "metageneration": 1,
  "generation": 1765525683660,
  "contentType": "audio/mpeg",
  "storageClass": "STANDARD",
  "contentDisposition": "inline",
  "downloadTokens": [
    "3be0a348-80b7-49c8-a509-be0e15e30f3a"
  ],
  "etag": "kICT7550ddokgNRqVnKqWmvVroA",
  "customMetadata": {},
  "timeCreated": "2025-12-12T07:48:03.660Z",
  "updated": "2025-12-12T07:48:03.660Z",
  "size": 8864,
  "md5Hash": "IUudAZa5ytjN1ENmW9fcgA==",
  "crc32c": "3716825370"
}